chronify/__init__.py
chronify/annual_time_range_generator.py
chronify/base_models.py
chronify/column_representative_time_range_generator.py
chronify/common.py
chronify/csv_io.py
chronify/csv_time_series_parser.py
chronify/datetime_range_generator.py
chronify/exceptions.py
chronify/hive_functions.py
chronify/index_time_range_generator.py
chronify/loggers.py
chronify/models.py
chronify/py.typed
chronify/representative_time_range_generator.py
chronify/schema_manager.py
chronify/store.py
chronify/time.py
chronify/time_configs.py
chronify/time_range_generator_base.py
chronify/time_range_generator_factory.py
chronify/time_series_checker.py
chronify/time_series_mapper.py
chronify/time_series_mapper_base.py
chronify/time_series_mapper_column_representative_to_datetime.py
chronify/time_series_mapper_datetime.py
chronify/time_series_mapper_index_time.py
chronify/time_series_mapper_representative.py
chronify/time_utils.py
chronify/time_zone_converter.py
chronify/_vendor/kyuubi/LICENSE
chronify/_vendor/kyuubi/README.md
chronify/_vendor/kyuubi/TCLIService/TCLIService-remote
chronify/_vendor/kyuubi/TCLIService/TCLIService.py
chronify/_vendor/kyuubi/TCLIService/__init__.py
chronify/_vendor/kyuubi/TCLIService/constants.py
chronify/_vendor/kyuubi/TCLIService/ttypes.py
chronify/_vendor/kyuubi/pyhive/__init__.py
chronify/_vendor/kyuubi/pyhive/common.py
chronify/_vendor/kyuubi/pyhive/exc.py
chronify/_vendor/kyuubi/pyhive/hive.py
chronify/_vendor/kyuubi/pyhive/presto.py
chronify/_vendor/kyuubi/pyhive/sasl_compat.py
chronify/_vendor/kyuubi/pyhive/sqlalchemy_hive.py
chronify/_vendor/kyuubi/pyhive/sqlalchemy_presto.py
chronify/_vendor/kyuubi/pyhive/sqlalchemy_trino.py
chronify/_vendor/kyuubi/pyhive/trino.py
chronify/duckdb/__init__.py
chronify/duckdb/functions.py
chronify/sqlalchemy/__init__.py
chronify/sqlalchemy/functions.py
chronify/utils/__init__.py
chronify/utils/path_utils.py
chronify/utils/sql.py
chronify/utils/sqlalchemy_table.py
chronify/utils/sqlalchemy_view.py
chronify-0.6.1.dist-info/METADATA
chronify-0.6.1.dist-info/WHEEL
chronify-0.6.1.dist-info/entry_points.txt
chronify-0.6.1.dist-info/licenses/LICENSE
chronify-0.6.1.dist-info/RECORD
