Metadata-Version: 2.4
Name: chronify
Version: 0.6.1
Summary: Time series store and mapping libray
Project-URL: Documentation, https://github.com/NREL/chronify#readme
Project-URL: Issues, https://github.com/NREL/chronify/issues
Project-URL: Source, https://github.com/NREL/chronify
Author-email: Daniel Thom <daniel.thom@nrel.gov>, Elaine Hale <elaine.hale@nrel.gov>, Lixi Liu <lixi.liu@nrel.gov>, Pedro Andres Sanchez Perez <pedroandres.sanchezperez@nrel.gov>
License-Expression: BSD-3-Clause
License-File: LICENSE
Classifier: Development Status :: 4 - Beta
Classifier: Programming Language :: Python
Classifier: Programming Language :: Python :: 3.10
Classifier: Programming Language :: Python :: 3.11
Classifier: Programming Language :: Python :: 3.12
Classifier: Programming Language :: Python :: Implementation :: CPython
Classifier: Programming Language :: Python :: Implementation :: PyPy
Requires-Python: <3.14,>=3.11
Requires-Dist: duckdb-engine
Requires-Dist: duckdb~=1.1.0
Requires-Dist: future
Requires-Dist: loguru
Requires-Dist: pandas<3,>=2.2
Requires-Dist: pyarrow
Requires-Dist: pydantic<3,>=2.7
Requires-Dist: python-dateutil
Requires-Dist: pytz
Requires-Dist: rich
Requires-Dist: sqlalchemy==2.0.37
Requires-Dist: tzdata
Provides-Extra: dev
Requires-Dist: autodoc-pydantic~=2.0; extra == 'dev'
Requires-Dist: furo; extra == 'dev'
Requires-Dist: mypy<2,>=1.15; extra == 'dev'
Requires-Dist: myst-parser; extra == 'dev'
Requires-Dist: pandas-stubs; extra == 'dev'
Requires-Dist: pre-commit; extra == 'dev'
Requires-Dist: pytest; extra == 'dev'
Requires-Dist: pytest-cov; extra == 'dev'
Requires-Dist: ruff; extra == 'dev'
Requires-Dist: sphinx; extra == 'dev'
Requires-Dist: sphinx-click; extra == 'dev'
Requires-Dist: sphinx-copybutton; extra == 'dev'
Requires-Dist: sphinx-tabs~=3.4; extra == 'dev'
Provides-Extra: spark
Requires-Dist: thrift; extra == 'spark'
Requires-Dist: thrift-sasl; extra == 'spark'
